v6_search/__init__.py
v6_search-1.0.0.dist-info/licenses/LICENSE
v6_search-1.0.0.dist-info/METADATA
v6_search-1.0.0.dist-info/WHEEL
v6_search-1.0.0.dist-info/top_level.txt
v6_search-1.0.0.dist-info/RECORD
