Metadata-Version: 2.4
Name: v6-search
Version: 1.0.0
Summary: Intelligent search algorithm V6 for Elasticsearch with multi-dimensional document retrieval
Author-email: 元龙居士 <your-email@example.com>
License: MIT
Project-URL: Homepage, https://github.com/yourusername/v6-search
Project-URL: Documentation, https://github.com/yourusername/v6-search#readme
Project-URL: Repository, https://github.com/yourusername/v6-search.git
Project-URL: Issues, https://github.com/yourusername/v6-search/issues
Keywords: search,elasticsearch,intelligent-search,document-retrieval,chinese-search
Classifier: Development Status :: 4 - Beta
Classifier: Intended Audience :: Developers
Classifier: License :: OSI Approved :: MIT License
Classifier: Programming Language :: Python :: 3
Classifier: Programming Language :: Python :: 3.7
Classifier: Programming Language :: Python :: 3.8
Classifier: Programming Language :: Python :: 3.9
Classifier: Programming Language :: Python :: 3.10
Classifier: Programming Language :: Python :: 3.11
Classifier: Topic :: Software Development :: Libraries :: Python Modules
Classifier: Topic :: Text Processing :: Indexing
Classifier: Topic :: Internet :: WWW/HTTP :: Indexing/Search
License-File: LICENSE
Requires-Dist: jieba>=0.42.1
Requires-Dist: requests>=2.28.0
Provides-Extra: dev
Requires-Dist: pytest>=7.0.0; extra == "dev"
Requires-Dist: black>=22.0.0; extra == "dev"
Requires-Dist: flake8>=5.0.0; extra == "dev"
Dynamic: license-file
